{"version": "https://jsonfeed.org/version/1", "title": "ZoomQuiet.io", "home_page_url": "https://zoomquiet.io/", "feed_url": "https://zoomquiet.io/feed_json_updated.json", "description": "\u5927\u5988\u7684\u4e3b\u9875", "icon": null, "authors": [{"name": "ZoomQuiet"}], "language": "zh", "items": [{"id": "https://zoomquiet.io/OldTouch/NGZK46/20250520-nnnewstar/", "url": "https://zoomquiet.io/OldTouch/NGZK46/20250520-nnnewstar/", "title": "\u7d2b\u2606S5", "content_html": "<h1>\u7d2b\u2606S5</h1>\n<blockquote>\n<p>2025\u5e74\u56db\u6708\u521a\u521a\u4e0a\u7ebf\u7684, \u53d2\u4e00\u671f\u7d2b\u661f\u8bde\u751f</p>\n</blockquote>\n<p>\u4e43\u6728\u574246 \u516d\u671f\u751f\u771f\u662f\u547d\u597d, \u4e0a\u5c97\u521a\u521a3\u5468\u5c31\u6709\u51a0\u540d\u8282\u76ee,\n- \u4e00\u671f\u71ac\u4e86\u534a\u5e74,\n- \u4e8c\u671f\u4e00\u76f4\u6ca1\u8f6e\u4e0a,\n- \u4e09\u671f\u6709\u4e00\u5806,\n- \u56db\u671f\u4e4b\u540e, \u57fa\u672c\u4e00\u5165\u5f79\u5c31\u76f4\u63a5\u4e0a\u4e86..</p>\n<h2>\u7d2b\u661f</h2>\n<blockquote>\n<p>\u4e43\u6728\u5742\u660e\u661f\u8bde\u751f \u8282\u76ee\u7684\u7b80\u79f0</p>\n</blockquote>\n<ul>\n<li>\u56e0\u4e3a \u4e43\u6728\u574246 \u7684 logo \u662f\u7d2b\u8272...</li>\n</ul>", "image": null, "date_modified": "2025-05-11T01:47:23.846584+00:00", "authors": [], "tags": null}, {"id": "https://zoomquiet.io/OldTouch/NGZK46/", "url": "https://zoomquiet.io/OldTouch/NGZK46/", "title": "\u4e43\u6728\u574246", "content_html": "<h1>\u4e43\u6728\u574246</h1>\n<blockquote>\n<p>\u6f02\u6d41\u996d\u7684\u55ef\u54fc</p>\n</blockquote>\n<h2>background</h2>\n<p>...TBD</p>\n<h2>goal</h2>\n<p>...TBD</p>\n<h2>trac</h2>\n<p>...TBD</p>\n<h2>refer.</h2>\n<p>...TBD</p>\n<p>```\n         <em>~\u223d-~~</em>\n     () /  - \u2609  \\ (/\n       '<em>   \ud835\udfc2   </em>'\n    ...</p>", "image": null, "date_modified": "2025-05-11T01:47:23.822169+00:00", "authors": [], "tags": null}, {"id": "https://zoomquiet.io/OldTouch/ANN/20250407-ANN-follow/", "url": "https://zoomquiet.io/OldTouch/ANN/20250407-ANN-follow/", "title": "Follow \u8ba2\u9605\u6e90", "content_html": "<h1>Follow \u8ba2\u9605\u6e90</h1>\n<blockquote>\n<p>This message is used to verify that this feed (feedId:132063759427328000) belongs to me (userId:68573755406424064). Join me in enjoying the n...</p>\n</blockquote>", "image": null, "date_modified": "2025-05-11T01:47:23.798209+00:00", "authors": [], "tags": null}, {"id": "https://zoomquiet.io/OldTouch/ANN/20200302-ZQ42-ANN-NINAN/", "url": "https://zoomquiet.io/OldTouch/ANN/20200302-ZQ42-ANN-NINAN/", "title": "\u516c\u544a/ \u5462\u5583", "content_html": "<h1>\u516c\u544a/ \u5462\u5583</h1>\n<pre><code>Title: \u516c\u544a/ \u5462\u5583:\u6536\u96c6 \u79c1\u4eba\u7247\u6bb5\nDate: 2020-03-02 10:42\nModified: 2020-03-05 15:35\nAuthors: ZoomQuiet\nCategory: ANN\nTags: ann, define,...\n</code></pre>", "image": null, "date_modified": "2025-05-11T01:47:23.773680+00:00", "authors": [], "tags": null}, {"id": "https://zoomquiet.io/OldTouch/ANN/20200223-ZoomQuiet42-ANN-0-aaaagin/", "url": "https://zoomquiet.io/OldTouch/ANN/20200223-ZoomQuiet42-ANN-0-aaaagin/", "title": "\u516c\u544a/ \u53d5\u91cd\u65b0\u5f00\u59cb\u7684\u5927\u5988", "content_html": "<h1>\u516c\u544a/ \u53d5\u91cd\u65b0\u5f00\u59cb\u7684\u5927\u5988</h1>\n<pre><code>Title: \u516c\u544a/ \u53d5\u91cd\u65b0\u5f00\u59cb\u7684\u5927\u5988\nDate: 2020-02-23 10:42\nModified: 2020-03-05 15:35\nAuthors: ZoomQuiet\nCategory: ANN\nTags: ann, def...\n</code></pre>", "image": null, "date_modified": "2025-05-11T01:47:23.749158+00:00", "authors": [], "tags": null}, {"id": "https://zoomquiet.io/OldTouch/ANN/20200222-ZQ42-ANN-historic/", "url": "https://zoomquiet.io/OldTouch/ANN/20200222-ZQ42-ANN-historic/", "title": "\u516c\u544a/ \u94a9\u9648", "content_html": "<h1>\u516c\u544a/ \u94a9\u9648</h1>\n<pre><code>Title: \u516c\u544a/ \u94a9\u9648\nDate: 2020-02-22 10:42\nModified: 2020-03-05 15:42\nAuthors: ZoomQuiet\nCategory: ANN\nkeywords: ann, define, Cat...\n</code></pre>", "image": null, "date_modified": "2025-05-11T01:47:23.721490+00:00", "authors": [], "tags": null}, {"id": "https://zoomquiet.io/OldTouch/ANN/20200222-ZQ42-ANN-IMHO/", "url": "https://zoomquiet.io/OldTouch/ANN/20200222-ZQ42-ANN-IMHO/", "title": "\u516c\u544a/ \u62d9\u89c1", "content_html": "<h1>\u516c\u544a/ \u62d9\u89c1</h1>\n<pre><code>Title: \u516c\u544a/ \u62d9\u89c1\nDate: 2020-02-22 11:42\nModified: 2020-03-05 15:45\nAuthors: ZoomQuiet\nCategory: ANN\nTags: ann, define, Category...\n</code></pre>", "image": null, "date_modified": "2025-05-11T01:47:23.696403+00:00", "authors": [], "tags": null}, {"id": "https://zoomquiet.io/OldTouch/ANN/20170910-pressone/", "url": "https://zoomquiet.io/OldTouch/ANN/20170910-pressone/", "title": "PRESSone", "content_html": "<h1>PRESSone</h1>\n<pre><code>Title: \u5173\u8054 PRESSone\nDate: 2017-09-10 08:42\nTags: pre, blockchain\nSlug: bind-press-one\nAuthor: Zoom.Quiet\n\n[TOC]\n</code></pre>\n<blockquote>\n<p>https:...</p>\n</blockquote>", "image": null, "date_modified": "2025-05-11T01:47:23.672580+00:00", "authors": [], "tags": null}, {"id": "https://zoomquiet.io/OldTouch/ANN/", "url": "https://zoomquiet.io/OldTouch/ANN/", "title": "\u901a\u544a", "content_html": "<h1>\u901a\u544a</h1>\n<blockquote>\n<p>\u5404\u79cd\u65f6\u671f\u7684...</p>\n</blockquote>\n<h2>background</h2>\n<p>...TBD</p>\n<h2>goal</h2>\n<p>...TBD</p>\n<h2>trac</h2>\n<p>...TBD</p>\n<h2>refer.</h2>\n<p>...TBD</p>", "image": null, "date_modified": "2025-05-11T01:47:23.647065+00:00", "authors": [], "tags": null}, {"id": "https://zoomquiet.io/", "url": "https://zoomquiet.io/", "title": "\u9996\u9875", "content_html": "<h1>\u9996\u9875</h1>\n<blockquote>\n<p>\u65e0\u6570\u6b21\u8fc1\u79fb\u540e...</p>\n</blockquote>\n<h2>updating...</h2>\n<blockquote>\n<p>\u6700\u65b0\u53d1\u5e03\u7684\u6587\u7ae0..\u6bd5\u7adf,\u8fd9\u662f\u4e2a\u56fe\u4e66\u7f51\u7ad9,\u60f3\u6309 blog \u7684\u65f6\u95f4\u987a\u5e8f\u770b,\u5f97\u989d\u5916\u6574\u7406..</p>\n<p>:::..</p>\n</blockquote>\n<ul>\n<li><a href='OldTouch/NGZK46/20250520-nnnewstar/'>\u7d2b\u2606S5</a></li>\n<li>&lt;a href...</li>\n</ul>", "image": null, "date_modified": "2025-05-11T00:14:14+00:00", "authors": [], "tags": null}, {"id": "https://zoomquiet.io/Pythonic/", "url": "https://zoomquiet.io/Pythonic/", "title": "Pythonic", "content_html": "<h1>Pythonic</h1>\n<blockquote>\n<p>\u6280\u672f\u611f\u60f3....</p>\n</blockquote>\n<h2>background</h2>\n<p>...TBD</p>\n<h2>goal</h2>\n<p>...TBD</p>\n<h2>trac</h2>\n<p>...TBD</p>\n<h2>refer.</h2>\n<p>...TBD</p>", "image": null, "date_modified": "2025-05-11T00:14:14+00:00", "authors": [], "tags": null}, {"id": "https://zoomquiet.io/Pythonic/25/", "url": "https://zoomquiet.io/Pythonic/25/", "title": "\u87d2\u6837@2025", "content_html": "<h1>\u87d2\u6837@2025</h1>\n<blockquote>\n<p>\u5404\u79cd Pytnonic \u6298\u817e</p>\n</blockquote>\n<h2>background</h2>\n<p>\u4f5c\u4e3a\u6807\u51c6 ie \u6df7\u5408\u4eba,\n\u5e73\u65f6\u603b\u662f\u503e\u5411\u5148\u81ea\u5df1\u6298\u817e,\n\u641e\u51fa\u70b9\u4e1c\u897f\u540e, \u518d\u56db\u5904\u55ef\u54fc...</p>\n<h2>goal</h2>\n<p>\u8bb0\u5f55\u6240\u6709 Pythonic \u7cbe\u795e\u6307\u5f15\u4e0b\u7684\u6298\u817e</p>\n<h2>trac</h2>\n<p>...TBD</p>\n<h2>refer.</h2>\n<p>...TBD</p>", "image": null, "date_modified": "2025-05-11T00:14:14+00:00", "authors": [], "tags": null}, {"id": "https://zoomquiet.io/Pythonic/25/20250510-graphivz-svg/", "url": "https://zoomquiet.io/Pythonic/25/20250510-graphivz-svg/", "title": "\u601d\u7ef4\u56fe\u8c31\u77e2\u91cf\u5316", "content_html": "<h1>\u601d\u7ef4\u56fe\u8c31\u77e2\u91cf\u5316</h1>\n<blockquote>\n<p>20\u5e74\u6765\u7684\u987f\u609f</p>\n</blockquote>\n<h2>background</h2>\n<p>zoomquiet.org \u56fe\u8c31\u5f0f\u9996\u9875\u521b\u5efa\u51fa20\u5e74, \u7a81\u7136\u53d1\u73b0\u53ef\u4ee5\u4e0d\u7528\u90a3\u4e48\u6298\u817e\u7684..</p>\n<h2>goal</h2>\n<blockquote>\n<p>\u5e94\u5bf9\u4e0a\u5343\u4e2a node \u7684\u590d\u6742\u56fe\u8c31\u65f6..</p>\n</blockquote>\n<ul>\n<li>\u4f53\u79ef\u5c3d\u53ef\u80fd\u5c0f</li>\n<li>\u652f\u6301\u6d4f\u89c8\u5668\u4e2d\u7684\u653e\u5927</li>\n<li>\u652f\u6301 .dot \u811a\u672c\u4e2d\u7684 URL \u914d\u7f6e</li>\n<li>...</li>\n</ul>", "image": null, "date_modified": "2025-05-11T00:14:14+00:00", "authors": [], "tags": null}, {"id": "https://zoomquiet.io/MurMur/20141223-zoomquiet4KO/", "url": "https://zoomquiet.io/MurMur/20141223-zoomquiet4KO/", "title": "KnewOne-talk \u4e4b \u5927\u5988 \u7bc7", "content_html": "<h1>KnewOne-talk \u4e4b \u5927\u5988 \u7bc7</h1>\n<pre><code>Title: KnewOne-talk \u4e4b \u5927\u5988 \u7bc7\nDate: 2014-12-23 23:23\nTags: MAC,Livin,Zoomq\nSlug: knewone-talk-zoomq-choise\n</code></pre>\n<p>~ KnewOne talk...</p>", "image": null, "date_modified": "2025-05-09T21:11:06+00:00", "authors": [], "tags": null}, {"id": "https://zoomquiet.io/MurMur/24/20240717-1/", "url": "https://zoomquiet.io/MurMur/24/20240717-1/", "title": "|> 240717 \u6668\u7cdf+1", "content_html": "<h1>|&gt; 240717 \u6668\u7cdf+1</h1>\n<p>\u7fa4\u91cc\u770b\u5230\u4e00\u7bc7\u6700\u65b0\u6587\u7ae0:\n<a href=\"https://mp.weixin.qq.com/s/BKQez6YyxyuDtTxgeHk1Kg\">\u63ed\u79d8\u82f9\u679c(Apple)\u516c\u53f8\u7684\u5f00\u6e90\u6839\u57fa\uff1amacOS\u548ciOS\u4e0eBSD\u7684\u5386\u53f2\u6e0a\u6e90\u53ca\u5176\u6df1\u8fdc\u5f71\u54cd</a></p>\n<p>\u4f5c\u8005\u66f0:</p>\n<blockquote>\n<p>\u8ba4\u8bc6\u5230 BSD \u5728\u82f9\u679c\u8f89\u714c\u5386\u7a0b\u4e2d\u7684\u6838\u5fc3\u5730\u4f4d\uff0c...</p>\n</blockquote>", "image": null, "date_modified": "2025-05-09T21:11:06+00:00", "authors": [], "tags": null}, {"id": "https://zoomquiet.io/MurMur/24/20240717/", "url": "https://zoomquiet.io/MurMur/24/20240717/", "title": "|> 240717 \u6668\u7cdf", "content_html": "<h1>|&gt; 240717 \u6668\u7cdf</h1>\n<p>\u300c\u6293\u5a03\u5a03\u300d\u4ffa\u6ca1\u53bb\u5f71\u9662\u770b,\u4e5f\u4e0d\u51c6\u5907\u5237\u4e0b\u8f7d\u89c6\u9891;\n\u8fd9\u4f53\u88c1\u542c\u7740\u5c31\u975e\u5e38\u5c34\u5c2c\u4e86...\n\u4e00\u7fa4\u5bcc\u8c6a\u62fc\u547d\u626e\u6f14\u7a77\u4eba,\n\u6700\u540e, happy endding,</p>\n<p>\u95ee\u9898, \u8fd9\u548c\u6700\u65e9\u7684 \u767e\u4e07\u82f1\u9551 (The Million Pound Note)\nhttps://movie.douban.com/subject...</p>", "image": null, "date_modified": "2025-05-09T21:11:06+00:00", "authors": [], "tags": null}, {"id": "https://zoomquiet.io/MurMur/24/20240718/", "url": "https://zoomquiet.io/MurMur/24/20240718/", "title": "|> 240718 \u6669\u5b89:", "content_html": "<h1>|&gt; 240718 \u6669\u5b89:</h1>\n<p><a href=\"https://www.youtube.com/watch?v=tSPPhdhvYLM\">\u3010\u81ea\u5a92\u4f53\u7684\u9053\u6cd5\u672f\u5668\u3011 \u8c28\u4ee5\u6b64\u7247\u732e\u7ed9\u90a3\u4e9b\u904d\u4f53\u9cde\u4f24\u7684\u81ea\u5a92\u4f53\u4eba\uff01\u8001\u80e160\u5206\u949f\u5bc6\u96c6\u5e72\u8d27\uff01 - YouTube</a></p>\n<p>\u8df3\u7740\u770b\u5b8c\u4e86, \u6bd5\u7adf\u770b\u5b57\u5e55\u6bd4\u542c\u7406\u89e3\u7684\u8981\u5feb\u5f88\u591a;</p>\n<p>\u81ea\u5df1\u7406\u89e3\u5230\u7684\u6838\u5fc3\u4e00\u70b9: <code>\u5229\u4ed6</code></p>\n<p>...</p>", "image": null, "date_modified": "2025-05-09T21:11:06+00:00", "authors": [], "tags": null}, {"id": "https://zoomquiet.io/MurMur/24/20240722/", "url": "https://zoomquiet.io/MurMur/24/20240722/", "title": "|> \u8c01\u62e5\u6709\u5e02\u573a, \u8c01\u5c31\u62e5\u6709\u667a\u6167:", "content_html": "<h1>|&gt; \u8c01\u62e5\u6709\u5e02\u573a, \u8c01\u5c31\u62e5\u6709\u667a\u6167:</h1>\n<p>Python \u5e94\u5bf9 Apple App Store \u7684\u62d2\u7edd [LWN.net] \nhttps://lwn.net/Articles/979671/</p>\n<blockquote>\n<p>...\u4ee4\u4eba\u6cae\u4e27\u7684\u662f\uff0c\u50cf Python \u8fd9\u6837\u7684\u81ea\u7531\u8f6f\u4ef6\u9879\u76ee\u4e0d\u5f97\u4e0d\u6d6a\u8d39\u65f6\u95f4\u5bfb\u627e\u7ed5\u8fc7\u4e0d\u900f\u660e\u5ba1\u67e5\u6d41\u7a0b\u7684\u65b9\u6cd5\uff0c\u4ee5\u4fbf\u5f00\u53d1\u4eba\u5458\u53ef\u4ee5\u4e3a\u975e...</p>\n</blockquote>", "image": null, "date_modified": "2025-05-09T21:11:06+00:00", "authors": [], "tags": null}, {"id": "https://zoomquiet.io/MurMur/24/20240725/", "url": "https://zoomquiet.io/MurMur/24/20240725/", "title": "|> 240725 \u6668\u7cdf:", "content_html": "<h1>|&gt; 240725 \u6668\u7cdf:</h1>\n<p>\u5728\u4e00\u5219 lark \u526a\u5b58\u4e2d\u770b\u5230: \n<a href=\"https://www.digitalnative.tech/p/how-ai-will-change-education\">How AI Will Change Education - by Rex Woodbury</a></p>\n<p>\u4e0d\u5f97\u4e0d\u53f9\u606f:\u5916\u56fd\u4eba\u7684\u6587...</p>", "image": null, "date_modified": "2025-05-09T21:11:06+00:00", "authors": [], "tags": null}, {"id": "https://zoomquiet.io/MurMur/24/20240727/", "url": "https://zoomquiet.io/MurMur/24/20240727/", "title": "|> 240727 \u6669\u5b89:", "content_html": "<h1>|&gt; 240727 \u6669\u5b89:</h1>\n<p>\u9694\u58c1\u7fa4\u8f6c\u53d1\u7f51\u53cb\u601d\u8003:</p>\n<blockquote>\n<p>..\u65bd\u5c55\u8001\u5e08\u7ed9\u51fa\u4e86\u4e00\u4e2a\u77e5\u8bc6\u5206\u5b50\u7684\u601d\u8003\uff5e\n\u2026 \u4ece\u800c\uff0c\u6570\u5b57\u6280\u672f\u5b9e\u9645\u4e0a\u4f1a\u6784\u9020\u51fa\u4e00\u79cd\u8d85\u56fd\u5bb6\u7684\u7a7a\u95f4\u79e9\u5e8f\uff0c\n\u8fd9\u91cc\u9762\u7684\u7ecf\u6d4e\u8fd0\u884c\u903b\u8f91\uff0c\u662f\u8ddf\u5176\u8fb9\u754c\u5c0f\u4e8e\u56fd\u5bb6\u7684\u4f20\u7edf\u4ea7\u4e1a\u5927\u4e0d\u4e00\u6837\u7684\u3002\n\u6253\u4e2a\u6bd4\u65b9\uff0c\u4e3b\u6743\u56fd\u5bb6\u79e9\u5e8f\u4ee5\u53ca\u57fa\u4e8e\u4e3b\u6743\u56fd\u5bb6\u79e9\u5e8f\u7684\u4f20\u7edf\u4ea7\u4e1a\uff0c\n\u662f\u5728\u4e8c\u7ef4\u7a7a\u95f4\u5f53\u4e2d\u6d3b\u52a8\u7684...</p>\n</blockquote>", "image": null, "date_modified": "2025-05-09T21:11:06+00:00", "authors": [], "tags": null}]}